{
  "milestone": "3.5: Calc-Bridge",
  "phase": 3,
  "phase_name": "Advanced Tooling",
  "objective": "Mathematical computation co-processor",
  "duration_weeks": 3,
  "task_count": 25,
  "dependencies": ["Phase-1-Foundation-MVP"],
  "deliverables": [
    "pkg/math/ with expression system",
    "pkg/parser/ with math parser",
    "pkg/symbolic/ with symbolic solver",
    "pkg/numerical/ with numerical engine",
    "cmd/calc-bridge/ tool executable",
    "Visualization capabilities",
    ">80% code coverage"
  ],
  "success_metrics": {
    "expression_parsing": "<10ms",
    "equation_solving": "accurate solutions",
    "code_coverage": ">80%",
    "test_pass_rate": "100%"
  },
  "capabilities": [
    "Symbolic equation solving",
    "Differentiation and integration",
    "Matrix operations",
    "Numerical computation",
    "Visualization",
    "LaTeX rendering"
  ],
  "key_components": {
    "expression_system": "pkg/math/expression.go",
    "parser": "pkg/parser/parser.go",
    "symbolic_solver": "pkg/symbolic/solver.go",
    "numerical_engine": "pkg/numerical/engine.go",
    "visualization": "pkg/viz/visualizer.go",
    "cli_tool": "cmd/calc-bridge/main.go"
  }
}
